COPYING
LICENSE
MANIFEST.in
README.rst
distribute_setup.py
rtd_requirements.txt
setup.py
Orange_NMF.egg-info/PKG-INFO
Orange_NMF.egg-info/SOURCES.txt
Orange_NMF.egg-info/dependency_links.txt
Orange_NMF.egg-info/entry_points.txt
Orange_NMF.egg-info/not-zip-safe
Orange_NMF.egg-info/requires.txt
Orange_NMF.egg-info/top_level.txt
_nmf/__init__.py
_nmf/widgets/OWMissingValues.py
_nmf/widgets/OWNMF.py
_nmf/widgets/OWNMFRankSelection.py
_nmf/widgets/OWNormalizationNMF.py
_nmf/widgets/OWPivotData.py
_nmf/widgets/OWSelectDataNMF.py
_nmf/widgets/OWrSVD.py
_nmf/widgets/__init__.py
_nmf/widgets/rSVD.py
_nmf/widgets/icons/MissingIcon.png
_nmf/widgets/icons/MissingIcon_16.png
_nmf/widgets/icons/MissingIcon_32.png
_nmf/widgets/icons/MissingIcon_40.png
_nmf/widgets/icons/MissingIcon_48.png
_nmf/widgets/icons/MissingIcon_60.png
_nmf/widgets/icons/NMFicon.png
_nmf/widgets/icons/NMFicon_16.png
_nmf/widgets/icons/NMFicon_32.png
_nmf/widgets/icons/NMFicon_40.png
_nmf/widgets/icons/NMFicon_48.png
_nmf/widgets/icons/NMFicon_60.png
_nmf/widgets/icons/NormalizeIcon.png
_nmf/widgets/icons/NormalizeIcon_16.png
_nmf/widgets/icons/NormalizeIcon_32.png
_nmf/widgets/icons/NormalizeIcon_40.png
_nmf/widgets/icons/NormalizeIcon_48.png
_nmf/widgets/icons/NormalizeIcon_60.png
_nmf/widgets/icons/PivotIcon.png
_nmf/widgets/icons/PivotIcon_16.png
_nmf/widgets/icons/PivotIcon_32.png
_nmf/widgets/icons/PivotIcon_40.png
_nmf/widgets/icons/PivotIcon_48.png
_nmf/widgets/icons/PivotIcon_60.png
_nmf/widgets/icons/RankSelectionIcon.png
_nmf/widgets/icons/RankSelectionIcon_16.png
_nmf/widgets/icons/RankSelectionIcon_32.png
_nmf/widgets/icons/RankSelectionIcon_40.png
_nmf/widgets/icons/RankSelectionIcon_48.png
_nmf/widgets/icons/RankSelectionIcon_60.png
_nmf/widgets/icons/SVDIcon.png
_nmf/widgets/icons/SVDIcon_16.png
_nmf/widgets/icons/SVDIcon_32.png
_nmf/widgets/icons/SVDIcon_40.png
_nmf/widgets/icons/SVDIcon_48.png
_nmf/widgets/icons/SVDIcon_60.png
docs/Makefile
docs/Orange-NMF_add-on.pdf
docs/README.txt
docs/canvas/shortDemo.ows
docs/canvas/testPivotWidget.ows
docs/canvas/workflow.ows
docs/rst/conf.py
docs/rst/index.rst
tests/__init__.py